JingeR/__init__.py
JingeR/__main__.py
JingeR/jinger.py
JingeR/templates/testcase.jinja.robot
JingeR/templates/testdata.py
robotframework_jinger-1.0.1.dist-info/entry_points.txt
robotframework_jinger-1.0.1.dist-info/LICENSE
robotframework_jinger-1.0.1.dist-info/WHEEL
robotframework_jinger-1.0.1.dist-info/METADATA
robotframework_jinger-1.0.1.dist-info/RECORD
