Metadata-Version: 2.1
Name: robotframework-jinger
Version: 1.0.1
Summary: Generate data-driven Robot Framework testcases using Jinja templates
Author-email: "Marduk Bolaños, Mohamad Nour Almujarkesh" <marduk.bolanos@imbus.de>
Requires-Python: >= 3.8.2
Requires-Dist: jinja2>=3.1.3
Requires-Dist: click>=8.1.7
Project-URL: homepage, https://github.com/mardukbp/robotframework-jinger
